setup.py
pdf_probability/Binomialdistribution.py
pdf_probability/Gaussiandistribution.py
pdf_probability/Generaldistribution.py
pdf_probability/__init__.py
pdf_probability.egg-info/PKG-INFO
pdf_probability.egg-info/SOURCES.txt
pdf_probability.egg-info/dependency_links.txt
pdf_probability.egg-info/not-zip-safe
pdf_probability.egg-info/top_level.txt